decorator_validation/__init__.py
decorator_validation/decorators.py
decorator_validation/helpers.py
decorator_validation/std_validators.py
decorator_validation/types.py
decorator_validation-4.1.0.dist-info/LICENSE
decorator_validation-4.1.0.dist-info/METADATA
decorator_validation-4.1.0.dist-info/WHEEL
decorator_validation-4.1.0.dist-info/RECORD
