Metadata-Version: 2.1
Name: decorator-validation
Version: 4.1.0
Summary: Fast Argument validation for functions using decorators
Home-page: https://github.com/ahartlba/decorator_validation
Author: FailedRobot
Author-email: sry@nomail.com
Requires-Python: >=3.8.1,<4.0.0
Classifier: Programming Language :: Python :: 3
Classifier: Programming Language :: Python :: 3.9
Classifier: Programming Language :: Python :: 3.10
Classifier: Programming Language :: Python :: 3.11
